Workbook

Sheet DATA_MASTER
A1: Отчетная дата | B1: Продукт | C1: Экспозиция, млрд руб. | D1: Резерв ECL, млрд руб. | E1: Переоценка ECL, млрд руб. | F1: Уровень ECL, % | G1: Стоимость кредитного риска, % | H1: Ставка по продукту, % | I1: Стоимость фондирования, %
A2: Report date | B2: Product | C2: Exposure, RUB bn | D2: ECL reserve, RUB bn | E2: ECL remeasurement, RUB bn | F2: ECL rate, % | G2: Credit cost, % | H2: Product rate, % | I2: Funding rate, %
A3: report_date | B3: product | C3: exposure | D3: ecl_reserve | E3: ecl_remeasurement | F3: ecl_rate | G3: credit_cost | H3: product_rate | I3: funding_rate
A4: 31.12.2023 | B4: Mortgage | C4: 3837.6 | D4: 36.9 | E4: 5.45 | F4: 0.0096153846 | G4: 0.0028780208 | H4: 0.0791 | I4: 0.119
A5: 31.12.2023 | B5: Consumer | C5: 1982.1 | D5: 283.7 | E5: 11.55 | F5: 0.14313102 | G5: 0.011809012 | H5: 0.1362 | I5: 0.119
A6: 31.12.2023 | B6: Auto | C6: 411.5 | D6: 17.9 | E6: 2.3 | F6: 0.043499392 | G6: 0.011327006 | H6: 0.1781 | I6: 0.119
A7: 31.12.2023 | B7: Cards | C7: 232 | D7: 40.1 | E7: 2 | F7: 0.17284483 | G7: 0.017470251 | H7: 0.2103 | I7: 0.1278
A8: 30.06.2024 | B8: Mortgage | C8: 3938.15 | D8: 39.4 | E8: 5.4 | F8: 0.010004698 | G8: 0.0027778671 | H8: 0.076 | I8: 0.134
A9: 30.06.2024 | B9: Consumer | C9: 2058.2 | D9: 291.7 | E9: 22.8 | F9: 0.14172578 | G9: 0.022572581 | H9: 0.154 | I9: 0.134
A10: 30.06.2024 | B10: Auto | C10: 532.05 | D10: 27.1 | E10: 9.3 | F10: 0.050935062 | G10: 0.039425574 | H10: 0.179 | I10: 0.134
A11: 30.06.2024 | B11: Cards | C11: 261.1 | D11: 45.2 | E11: 6.3 | F11: 0.17311375 | G11: 0.051105252 | H11: 0.259 | I11: 0.163
A12: 31.12.2024 | B12: Mortgage | C12: 4038.7 | D12: 45.5 | E12: 7.2 | F12: 0.011266001 | G12: 0.0036104477 | H12: 0.085 | I12: 0.209
A13: 31.12.2024 | B13: Consumer | C13: 2134.3 | D13: 251.6 | E13: 11.3 | F13: 0.11788408 | G13: 0.010781157 | H13: 0.192 | I13: 0.209
A14: 31.12.2024 | B14: Auto | C14: 652.6 | D14: 54.4 | E14: 27.7 | F14: 0.083358872 | G14: 0.093529735 | H14: 0.223 | I14: 0.209
A15: 31.12.2024 | B15: Cards | C15: 290.2 | D15: 38.8 | E15: 8.6 | F15: 0.1337009 | G15: 0.062397968 | H15: 0.327 | I15: 0.214
... A27: 30.06.2026 | B27: Cards | C27: 223.4 | D27: 47 | E27: 6.6 | F27: 0.21038496 | G27: 0.055896676 | H27: 0.312 | I27: 0.13

Sheet SOURCES
A1: Документ | B1: Источник
A2: ВТБ — МСФО 2024 | B2: https://www.vtb.ru/media-files/vtb.ru/sitepages/ir/statements/results/ifrs_2024_rus.pdf
A3: ВТБ — МСФО 6М2025 | B3: https://www.vtb.ru/media-files/vtb.ru/sitepages/ir/statements/results/rus-vtb-group-ifrs-as-of-30-june-2025.pdf
A4: ВТБ — МСФО 2025 | B4: https://www.vtb.ru/media-files/vtb.ru/sitepages/ir/statements/results/rus-vtb-group-ifrs-as-of-31-december-2025.pdf
A5: ВТБ — МСФО 6М2026 | B5: https://www.vtb.ru/media-files/vtb.ru/sitepages/ir/statements/results/rus-vtb-group-ifrs-as-of-30-june-2026.pdf
A6: Официальный архив: | B6: https://www.vtb.ru/ir/statements/results/
A7: Процентные ставки по кредитам | B7: https://www.cbr.ru/statistics/bank_sector/int_rat/0626/
A8: ВТБ — динамика NIM 3К2025 | B8: https://vtbrussia.ru/media-files/vtb.ru/sitepages/ir/statements/results/call_transcript_0925_rus.pdf
A9: ВТБ — годовой отчет 2025 | B9: https://arvtb2025.ru/
A10: ВТБ — результаты 6М2024 (NIM 2,1%) | B10: https://www.vtb.ru/ir/statements/results/
A11: ВТБ — результаты 9М2024 (Q3 NIM 1,8%) | B11: https://www.vtb.ru/ir/statements/results/
A12: ВТБ — результаты 2024 (Q4 NIM 0,8%) | B12: https://www.vtb.ru/ir/statements/results/
... A17: Банк России — процентные ставки | B17: https://www.cbr.ru/statistics/bank_sector/int_rat/

Sheet MODEL_DATA
A1: Риск-скорректированный результат, млрд руб. | B1: Отчетная дата | C1: Период | D1: Продукт | E1: Экспозиция, млрд руб. | F1: Стоимость кредитного риска, % | G1: Рыночный pricing proxy, % | H1: Якорь средней маржи, % | I1: Коэффициент передачи λ | J1: Средневзвешенный pricing proxy, % | K1: Синтетическая маржа до кредитного риска, % | L1: Риск-скорректированная ставка, % | M1: Коэффициент периода
A2: Risk-adjusted result, RUB bn | B2: Report date | C2: Period | D2: Product | E2: Exposure, RUB bn | F2: Credit cost, % | G2: Market pricing proxy, % | H2: Average margin anchor, % | I2: Pass-through coefficient λ | J2: Weighted pricing proxy, % | K2: Synthetic pre-credit margin, % | L2: Risk-adjusted rate, % | M2: Period factor
A3: risk_adjusted_result | B3: report_date | C3: period | D3: product | E3: exposure | F3: credit_cost | G3: product_rate_proxy | H3: margin_anchor | I3: lambda | J3: weighted_product_rate | K3: synthetic_margin | L3: risk_adjusted_rate | M3: period_factor
A4: =E4*L4*M4 -> 41.095373 | B4: =DATA_MASTER!A4 -> 31.12.2023 | C4: 2023H2 | D4: =DATA_MASTER!B4 -> Mortgage | E4: =DATA_MASTER!C4 -> 3837.6 | F4: =DATA_MASTER!G4 -> 0.0028780208 | G4: =DATA_MASTER!H4 -> 0.0791 | H4: 0.03 | I4: 0.2 | J4: =SUMPRODUCT($E$4:$E$7,$G$4:$G$7)/SUM($E$4:$E$7) -> 0.10762377 | K4: =H4+I4*(G4-J4) -> 0.024295247 | L4: =K4-F4 -> 0.021417226 | M4: 0.5
A5: =E5*L5*M5 -> 23.692274 | B5: =DATA_MASTER!A5 -> 31.12.2023 | C5: 2023H2 | D5: =DATA_MASTER!B5 -> Consumer | E5: =DATA_MASTER!C5 -> 1982.1 | F5: =DATA_MASTER!G5 -> 0.011809012 | G5: =DATA_MASTER!H5 -> 0.1362 | H5: 0.03 | I5: 0.2 | J5: =SUMPRODUCT($E$4:$E$7,$G$4:$G$7)/SUM($E$4:$E$7) -> 0.10762377 | K5: =H5+I5*(G5-J5) -> 0.035715247 | L5: =K5-F5 -> 0.023906235 | M5: 0.5
A6: =E6*L6*M6 -> 6.7420655 | B6: =DATA_MASTER!A6 -> 31.12.2023 | C6: 2023H2 | D6: =DATA_MASTER!B6 -> Auto | E6: =DATA_MASTER!C6 -> 411.5 | F6: =DATA_MASTER!G6 -> 0.011327006 | G6: =DATA_MASTER!H6 -> 0.1781 | H6: 0.03 | I6: 0.2 | J6: =SUMPRODUCT($E$4:$E$7,$G$4:$G$7)/SUM($E$4:$E$7) -> 0.10762377 | K6: =H6+I6*(G6-J6) -> 0.044095247 | L6: =K6-F6 -> 0.032768241 | M6: 0.5
A7: =E7*L7*M7 -> 3.8355395 | B7: =DATA_MASTER!A7 -> 31.12.2023 | C7: 2023H2 | D7: =DATA_MASTER!B7 -> Cards | E7: =DATA_MASTER!C7 -> 232 | F7: =DATA_MASTER!G7 -> 0.017470251 | G7: =DATA_MASTER!H7 -> 0.2103 | H7: 0.03 | I7: 0.2 | J7: =SUMPRODUCT($E$4:$E$7,$G$4:$G$7)/SUM($E$4:$E$7) -> 0.10762377 | K7: =H7+I7*(G7-J7) -> 0.050535247 | L7: =K7-F7 -> 0.033064996 | M7: 0.5
A8: =E8*L8*M8 -> 20.618737 | B8: =DATA_MASTER!A8 -> 30.06.2024 | C8: 2024H1 | D8: =DATA_MASTER!B8 -> Mortgage | E8: =DATA_MASTER!C8 -> 3938.15 | F8: =DATA_MASTER!G8 -> 0.0027778671 | G8: =DATA_MASTER!H8 -> 0.076 | H8: 0.021 | I8: 0.2 | J8: =SUMPRODUCT($E$8:$E$11,$G$8:$G$11)/SUM($E$8:$E$11) -> 0.11475426 | K8: =H8+I8*(G8-J8) -> 0.013249148 | L8: =K8-F8 -> 0.010471281 | M8: 0.5
A9: =E9*L9*M9 -> 6.4592148 | B9: =DATA_MASTER!A9 -> 30.06.2024 | C9: 2024H1 | D9: =DATA_MASTER!B9 -> Consumer | E9: =DATA_MASTER!C9 -> 2058.2 | F9: =DATA_MASTER!G9 -> 0.022572581 | G9: =DATA_MASTER!H9 -> 0.154 | H9: 0.021 | I9: 0.2 | J9: =SUMPRODUCT($E$8:$E$11,$G$8:$G$11)/SUM($E$8:$E$11) -> 0.11475426 | K9: =H9+I9*(G9-J9) -> 0.028849148 | L9: =K9-F9 -> 0.0062765667 | M9: 0.5
A10: =E10*L10*M10 -> -1.4834686 | B10: =DATA_MASTER!A10 -> 30.06.2024 | C10: 2024H1 | D10: =DATA_MASTER!B10 -> Auto | E10: =DATA_MASTER!C10 -> 532.05 | F10: =DATA_MASTER!G10 -> 0.039425574 | G10: =DATA_MASTER!H10 -> 0.179 | H10: 0.021 | I10: 0.2 | J10: =SUMPRODUCT($E$8:$E$11,$G$8:$G$11)/SUM($E$8:$E$11) -> 0.11475426 | K10: =H10+I10*(G10-J10) -> 0.033849148 | L10: =K10-F10 -> -0.0055764257 | M10: 0.5
A11: =E11*L11*M11 -> -0.16398445 | B11: =DATA_MASTER!A11 -> 30.06.2024 | C11: 2024H1 | D11: =DATA_MASTER!B11 -> Cards | E11: =DATA_MASTER!C11 -> 261.1 | F11: =DATA_MASTER!G11 -> 0.051105252 | G11: =DATA_MASTER!H11 -> 0.259 | H11: 0.021 | I11: 0.2 | J11: =SUMPRODUCT($E$8:$E$11,$G$8:$G$11)/SUM($E$8:$E$11) -> 0.11475426 | K11: =H11+I11*(G11-J11) -> 0.049849148 | L11: =K11-F11 -> -0.0012561045 | M11: 0.5
A12: =E12*L12*M12 -> -3.0981502 | B12: =DATA_MASTER!A12 -> 31.12.2024 | C12: 2024H2 | D12: =DATA_MASTER!B12 -> Mortgage | E12: =DATA_MASTER!C12 -> 4038.7 | F12: =DATA_MASTER!G12 -> 0.0036104477 | G12: =DATA_MASTER!H12 -> 0.085 | H12: 0.013 | I12: 0.2 | J12: =SUMPRODUCT($E$12:$E$15,$G$12:$G$15)/SUM($E$12:$E$15) -> 0.13961892 | K12: =H12+I12*(G12-J12) -> 0.0020762163 | L12: =K12-F12 -> -0.0015342314 | M12: 0.5
A13: =E13*L13*M13 -> 13.547533 | B13: =DATA_MASTER!A13 -> 31.12.2024 | C13: 2024H2 | D13: =DATA_MASTER!B13 -> Consumer | E13: =DATA_MASTER!C13 -> 2134.3 | F13: =DATA_MASTER!G13 -> 0.010781157 | G13: =DATA_MASTER!H13 -> 0.192 | H13: 0.013 | I13: 0.2 | J13: =SUMPRODUCT($E$12:$E$15,$G$12:$G$15)/SUM($E$12:$E$15) -> 0.13961892 | K13: =H13+I13*(G13-J13) -> 0.023476216 | L13: =K13-F13 -> 0.012695059 | M13: 0.5
A14: =E14*L14*M14 -> -20.835403 | B14: =DATA_MASTER!A14 -> 31.12.2024 | C14: 2024H2 | D14: =DATA_MASTER!B14 -> Auto | E14: =DATA_MASTER!C14 -> 652.6 | F14: =DATA_MASTER!G14 -> 0.093529735 | G14: =DATA_MASTER!H14 -> 0.223 | H14: 0.013 | I14: 0.2 | J14: =SUMPRODUCT($E$12:$E$15,$G$12:$G$15)/SUM($E$12:$E$15) -> 0.13961892 | K14: =H14+I14*(G14-J14) -> 0.029676216 | L14: =K14-F14 -> -0.063853518 | M14: 0.5
A15: =E15*L15*M15 -> -1.7298462 | B15: =DATA_MASTER!A15 -> 31.12.2024 | C15: 2024H2 | D15: =DATA_MASTER!B15 -> Cards | E15: =DATA_MASTER!C15 -> 290.2 | F15: =DATA_MASTER!G15 -> 0.062397968 | G15: =DATA_MASTER!H15 -> 0.327 | H15: 0.013 | I15: 0.2 | J15: =SUMPRODUCT($E$12:$E$15,$G$12:$G$15)/SUM($E$12:$E$15) -> 0.13961892 | K15: =H15+I15*(G15-J15) -> 0.050476216 | L15: =K15-F15 -> -0.011921752 | M15: 0.5
A16: =E16*L16*M16 -> -12.070341 | B16: =DATA_MASTER!A16 -> 30.06.2025 | C16: 2025H1 | D16: =DATA_MASTER!B16 -> Mortgage | E16: =DATA_MASTER!C16 -> 4052.6 | F16: =DATA_MASTER!G16 -> 0.0053390679 | G16: =DATA_MASTER!H16 -> 0.075 | H16: 0.009 | I16: 0.2 | J16: =SUMPRODUCT($E$16:$E$19,$G$16:$G$19)/SUM($E$16:$E$19) -> 0.12308885 | K16: =H16+I16*(G16-J16) -> -0.00061777043 | L16: =K16-F16 -> -0.0059568383 | M16: 0.5
A17: =E17*L17*M17 -> -17.175638 | B17: =DATA_MASTER!A17 -> 30.06.2025 | C17: 2025H1 | D17: =DATA_MASTER!B17 -> Consumer | E17: =DATA_MASTER!C17 -> 1889.2 | F17: =DATA_MASTER!G17 -> 0.039965204 | G17: =DATA_MASTER!H17 -> 0.187 | H17: 0.009 | I17: 0.2 | J17: =SUMPRODUCT($E$16:$E$19,$G$16:$G$19)/SUM($E$16:$E$19) -> 0.12308885 | K17: =H17+I17*(G17-J17) -> 0.02178223 | L17: =K17-F17 -> -0.018182975 | M17: 0.5
A18: =E18*L18*M18 -> -19.610736 | B18: =DATA_MASTER!A18 -> 30.06.2025 | C18: 2025H1 | D18: =DATA_MASTER!B18 -> Auto | E18: =DATA_MASTER!C18 -> 614.1 | F18: =DATA_MASTER!G18 -> 0.083050446 | G18: =DATA_MASTER!H18 -> 0.174 | H18: 0.009 | I18: 0.2 | J18: =SUMPRODUCT($E$16:$E$19,$G$16:$G$19)/SUM($E$16:$E$19) -> 0.12308885 | K18: =H18+I18*(G18-J18) -> 0.01918223 | L18: =K18-F18 -> -0.063868216 | M18: 0.5
A19: =E19*L19*M19 -> -3.8395811 | B19: =DATA_MASTER!A19 -> 30.06.2025 | C19: 2025H1 | D19: =DATA_MASTER!B19 -> Cards | E19: =DATA_MASTER!C19 -> 276.8 | F19: =DATA_MASTER!G19 -> 0.067724868 | G19: =DATA_MASTER!H19 -> 0.278 | H19: 0.009 | I19: 0.2 | J19: =SUMPRODUCT($E$16:$E$19,$G$16:$G$19)/SUM($E$16:$E$19) -> 0.12308885 | K19: =H19+I19*(G19-J19) -> 0.03998223 | L19: =K19-F19 -> -0.027742638 | M19: 0.5
A20: =E20*L20*M20 -> 8.2026569 | B20: =DATA_MASTER!A20 -> 31.12.2025 | C20: 2025H2 | D20: =DATA_MASTER!B20 -> Mortgage | E20: =DATA_MASTER!C20 -> 4364.8 | F20: =DATA_MASTER!G20 -> 0.0075082567 | G20: =DATA_MASTER!H20 -> 0.076 | H20: 0.0175 | I20: 0.2 | J20: =SUMPRODUCT($E$20:$E$23,$G$20:$G$23)/SUM($E$20:$E$23) -> 0.10716597 | K20: =H20+I20*(G20-J20) -> 0.011266805 | L20: =K20-F20 -> 0.0037585488 | M20: 0.5
A21: =E21*L21*M21 -> 2.2059334 | B21: =DATA_MASTER!A21 -> 31.12.2025 | C21: 2025H2 | D21: =DATA_MASTER!B21 -> Consumer | E21: =DATA_MASTER!C21 -> 1644.8 | F21: =DATA_MASTER!G21 -> 0.022184493 | G21: =DATA_MASTER!H21 -> 0.144 | H21: 0.0175 | I21: 0.2 | J21: =SUMPRODUCT($E$20:$E$23,$G$20:$G$23)/SUM($E$20:$E$23) -> 0.10716597 | K21: =H21+I21*(G21-J21) -> 0.024866805 | L21: =K21-F21 -> 0.002682312 | M21: 0.5
A22: =E22*L22*M22 -> -8.4268411 | B22: =DATA_MASTER!A22 -> 31.12.2025 | C22: 2025H2 | D22: =DATA_MASTER!B22 -> Auto | E22: =DATA_MASTER!C22 -> 560.7 | F22: =DATA_MASTER!G22 -> 0.059925094 | G22: =DATA_MASTER!H22 -> 0.169 | H22: 0.0175 | I22: 0.2 | J22: =SUMPRODUCT($E$20:$E$23,$G$20:$G$23)/SUM($E$20:$E$23) -> 0.10716597 | K22: =H22+I22*(G22-J22) -> 0.029866805 | L22: =K22-F22 -> -0.030058288 | M22: 0.5
A23: =E23*L23*M23 -> -0.3727914 | B23: =DATA_MASTER!A23 -> 31.12.2025 | C23: 2025H2 | D23: =DATA_MASTER!B23 -> Cards | E23: =DATA_MASTER!C23 -> 248.9 | F23: =DATA_MASTER!G23 -> 0.053262317 | G23: =DATA_MASTER!H23 -> 0.271 | H23: 0.0175 | I23: 0.2 | J23: =SUMPRODUCT($E$20:$E$23,$G$20:$G$23)/SUM($E$20:$E$23) -> 0.10716597 | K23: =H23+I23*(G23-J23) -> 0.050266805 | L23: =K23-F23 -> -0.0029955114 | M23: 0.5
A24: =E24*L24*M24 -> 26.751559 | B24: =DATA_MASTER!A24 -> 30.06.2026 | C24: 2026H1 | D24: =DATA_MASTER!B24 -> Mortgage | E24: =DATA_MASTER!C24 -> 4279.8 | F24: =DATA_MASTER!G24 -> 0.0068019342 | G24: =DATA_MASTER!H24 -> 0.09 | H24: 0.026 | I24: 0.2 | J24: =SUMPRODUCT($E$24:$E$27,$G$24:$G$27)/SUM($E$24:$E$27) -> 0.12348377 | K24: =H24+I24*(G24-J24) -> 0.019303247 | L24: =K24-F24 -> 0.012501312 | M24: 0.5
A25: =E25*L25*M25 -> -4.7387013 | B25: =DATA_MASTER!A25 -> 30.06.2026 | C25: 2026H1 | D25: =DATA_MASTER!B25 -> Consumer | E25: =DATA_MASTER!C25 -> 1525.9 | F25: =DATA_MASTER!G25 -> 0.042514271 | G25: =DATA_MASTER!H25 -> 0.175 | H25: 0.026 | I25: 0.2 | J25: =SUMPRODUCT($E$24:$E$27,$G$24:$G$27)/SUM($E$24:$E$27) -> 0.12348377 | K25: =H25+I25*(G25-J25) -> 0.036303247 | L25: =K25-F25 -> -0.0062110247 | M25: 0.5
A26: =E26*L26*M26 -> -2.4887226 | B26: =DATA_MASTER!A26 -> 30.06.2026 | C26: 2026H1 | D26: =DATA_MASTER!B26 -> Auto | E26: =DATA_MASTER!C26 -> 543.9 | F26: =DATA_MASTER!G26 -> 0.043454644 | G26: =DATA_MASTER!H26 -> 0.165 | H26: 0.026 | I26: 0.2 | J26: =SUMPRODUCT($E$24:$E$27,$G$24:$G$27)/SUM($E$24:$E$27) -> 0.12348377 | K26: =H26+I26*(G26-J26) -> 0.034303247 | L26: =K26-F26 -> -0.0091513976 | M26: 0.5
A27: =E27*L27*M27 -> 0.87199396 | B27: =DATA_MASTER!A27 -> 30.06.2026 | C27: 2026H1 | D27: =DATA_MASTER!B27 -> Cards | E27: =DATA_MASTER!C27 -> 223.4 | F27: =DATA_MASTER!G27 -> 0.055896676 | G27: =DATA_MASTER!H27 -> 0.312 | H27: 0.026 | I27: 0.2 | J27: =SUMPRODUCT($E$24:$E$27,$G$24:$G$27)/SUM($E$24:$E$27) -> 0.12348377 | K27: =H27+I27*(G27-J27) -> 0.063703247 | L27: =K27-F27 -> 0.0078065708 | M27: 0.5
